jaguardb_http_client/JaguarHttpClient.py
jaguardb_http_client/LICENSE
jaguardb_http_client/README-http.md
jaguardb_http_client/__init__.py
jaguardb_http_client-3.5.0.1.data/data/jaguardb/JaguarHttpClient.py
jaguardb_http_client-3.5.0.1.data/data/jaguardb/LICENSE
jaguardb_http_client-3.5.0.1.data/data/jaguardb/README-http.md
jaguardb_http_client-3.5.0.1.dist-info/METADATA
jaguardb_http_client-3.5.0.1.dist-info/WHEEL
jaguardb_http_client-3.5.0.1.dist-info/top_level.txt
jaguardb_http_client-3.5.0.1.dist-info/RECORD
